Metadata-Version: 2.1
Name: dataModul13
Version: 1.1
Summary: Syntax:		function: data("{data}")# saved data;		function; read(); read data		function encode() encode data		function decode() decode data		example:		from dataModul import *;		test=data("ABC");		test.encode();		print(test.read());		test.decode();		print(test.read());				Console:		{0}{1}{2}		abc
Author-email: pyprogrammer13@gmail.com
